Workbook

Sheet Project Budget
D1: Restoring Hope - Project Budget
A2: Project Code | B2: RH-2025-0006 | C2: Date of Submission: 14th of Nov 2025 | I2: Total Project Budget | J2: 921200 | K2: USD
A3: Donor | B3: Qatar Charity | C3: Project Duration 12 Months | I3: Remaining Budget | J3: =J2-L40 -> 25.991 | K3: USD
A4: Budget Line | B4: Location | C4: Description | D4: UNIT | E4: # of Unit | F4: Freq | G4: curr | H4: unit price | I4: Covering percentage from this project | J4: Total | K4: Total in Euro | L4: Total in USD | M4: Budget Narrative | N4: Means of Verfication
A6: SAL_8 | B6: Amm | C6: Program Director | D6: Months | E6: 1 | F6: 12 | G6: JOD | H6: 3500 | I6: 0 | J6: =E6*F6*H6*I6 -> 0 | K6: =J6*1.23 -> 0 | L6: =J6*1.41 -> 0
A7: SAL_9 | B7: Gaza | C7: Project Manager (GAZA) | D7: Months | E7: 1 | F7: 12 | G7: JOD | H7: 2100 | I7: 0 | J7: =E7*F7*H7*I7 -> 0 | K7: =J7*1.23 -> 0 | L7: =J7*1.41 -> 0
A8: SAL_10 | B8: Amm | C8: MEAL Team Leader | D8: Months | E8: 1 | F8: 12 | G8: JOD | H8: 1200 | I8: 0 | J8: =E8*F8*H8*I8 -> 0 | K8: =J8*1.23 -> 0 | L8: =J8*1.41 -> 0
A9: SAL_11 | B9: Gaza | C9: Gaza Technical Officer | D9: Months | E9: 1 | F9: 12 | G9: JOD | H9: 700 | I9: 0 | J9: =E9*F9*H9*I9 -> 0 | K9: =J9*1.23 -> 0 | L9: =J9*1.41 -> 0
A10: SAL_12 | B10: Gaza | C10: Gaza Technical Officer | D10: Months | E10: 1 | F10: 12 | G10: JOD | H10: 700 | I10: 0 | J10: =E10*F10*H10*I10 -> 0 | K10: =J10*1.23 -> 0 | L10: =J10*1.41 -> 0
A11: SAL_13 | B11: Amm | C11: Amman Technical Officer | D11: Months | E11: 1 | F11: 12 | G11: JOD | H11: 1500 | I11: 0 | J11: =E11*F11*H11*I11 -> 0 | K11: =J11*1.23 -> 0 | L11: =J11*1.41 -> 0
A12: SAL_16 | B12: Amm | C12: Finance and Support Function Manager | D12: Months | E12: 1 | F12: 12 | G12: JOD | H12: 3500 | I12: 0 | J12: =E12*F12*H12*I12 -> 0 | K12: =J12*1.23 -> 0 | L12: =J12*1.41 -> 0
A13: SAL_17 | B13: Amm | C13: Supply Chain Officer | D13: Months | E13: 1 | F13: 12 | G13: JOD | H13: 550 | I13: 0 | J13: =E13*F13*H13*I13 -> 0 | K13: =J13*1.23 -> 0 | L13: =J13*1.41 -> 0
A14: SAL_18 | B14: Amm | C14: Driver | D14: Months | E14: 1 | F14: 12 | G14: JOD | H14: 300 | I14: 0 | J14: =E14*F14*H14*I14 -> 0 | K14: =J14*1.23 -> 0 | L14: =J14*1.41 -> 0
A15: SAL_19 | B15: Amm | C15: Admin Staff | D15: Months | E15: 1 | F15: 12 | G15: JOD | H15: 900 | I15: 0 | J15: =E15*F15*H15*I15 -> 0 | K15: =J15*1.23 -> 0 | L15: =J15*1.41 -> 0
A16: SAL_22 | B16: Amm | C16: Health Insurance | D16: Lum | E16: 1 | F16: 1 | G16: JOD | H16: 10000 | I16: 0 | J16: =E16*F16*H16*I16 -> 0 | K16: =J16*1.23 -> 0 | L16: =J16*1.41 -> 0
A17: SAL_23 | B17: Amm | C17: Social Security | D17: Lum | E17: 1 | F17: 1 | G17: JOD | H17: 25000 | I17: 0 | J17: =E17*F17*H17*I17 -> 0 | K17: =J17*1.23 -> 0 | L17: =J17*1.41 -> 0
A18: Total Personel | J18: =SUM(J6:J17) -> 0 | K18: =J18*1.23 -> 0 | L18: =J18*1.41 -> 0
A19: Office and Utilities Cost
A20: OFC001 | B20: Amm | C20: Office Rent Cost | D20: Months | E20: 12 | F20: 1 | G20: JOD | H20: 2500 | I20: 0 | J20: =I20*H20*F20*E20 -> 0 | K20: =J20*1.23 -> 0 | L20: =J20*1.41 -> 0
A21: EQP001 | B21: Amm | C21: IT Equipment | D21: Units | E21: 4 | F21: 1 | G21: JOD | H21: 700 | I21: 0 | J21: =I21*H21*F21*E21 -> 0 | K21: =J21*1.23 -> 0 | L21: =J21*1.41 -> 0
A22: EQP00215:2214:22C2817:2215:2216:2217:222:22 | B22: Gaza | C22: Field Equipment | D22: Units | E22: 3 | F22: 1 | G22: JOD | H22: 700 | I22: 0 | J22: =I22*H22*F22*E22 -> 0 | K22: =J22*1.23 -> 0 | L22: =J22*1.41 -> 0
A23: EQP003 | B23: Amm and Gaza | C23: Visability | D23: Lum | E23: 1 | F23: 1 | G23: JOD | H23: 5000 | I23: 0 | J23: =I23*H23*F23*E23 -> 0 | K23: =J23*1.23 -> 0 | L23: =J23*1.41 -> 0
A24: Total Office and Utilities | J24: =SUM(J20:J23) -> 0 | K24: =SUM(K20:K23) -> 0 | L24: =SUM(L20:L23) -> 0
A25: Personel | O25: QC commnets | P25: RHS Response
A26: Prog_1 | B26: Gaza | C26: Prosthetics Cost | D26: Lum | E26: 1 | F26: 1 | G26: JOD | H26: =446550.9+47822 -> 494372.9 | I26: 1 | J26: =I26*H26*F26*E26 -> 494372.9 | K26: =J26*1.23 -> 608078.67 | L26: =J26*1.41 -> 697065.79 | M26: Prosthetic components to support amputees in Gaza were procured from Ottobock, one of the world’s leading and highest-quality prosthetics manufacturers. These items have already been ordered and received, ensuring timely availability for beneficiary rehabilitation. | N26: Purchase Request, Purchase order, Goods Received note (GRN), Handover certificate (Hamad Hospital), and, Donation certificate | O26: Please provide all invoices too | P26: Add 67K to this line for an additional 15 above-knee prosthetics Budget line amended to reflect this
A27: Prog_2 | B27: Gaza | C27: Mental Helth Sessions Cost | D27: Session | E27: 2000 | F27: 1 | G27: JOD | H27: 18 | I27: 1 | J27: =I27*H27*F27*E27 -> 36000 | K27: =J27*1.23 -> 44280 | L27: =J27*1.41 -> 50760 | M27: Based on case-by-case needs, not all 600+ beneficiaries will require mental health support. It is estimated that approximately 80% of the target population will need mental health sessions, with an average of four sessions per individual. This results in an estimated total of 2,000 sessions, budgeted at 18 JOD per session. Any underspend resulting from lower-than-anticipated utilization will be reallocated toward the procurement of assistive devices to support beneficiary rehabilitation needs. | N27: List of benificiraies, Registration sheet and sessions attendance sheets | O27: no reallocation without prior approval | P27: Agreed
A28: Prog_3 | B28: Gaza | C28: Physical rehabilitation Sessions Cost | D28: Session | E28: 2000 | F28: 1 | G28: JOD | H28: 18 | I28: 1 | J28: =I28*H28*F28*E28 -> 36000 | K28: =J28*1.23 -> 44280 | L28: =J28*1.41 -> 50760 | M28: As rehabilitation needs vary across cases, not all 600+ beneficiaries will require the same level of therapy. It is estimated that approximately 80% of the total target group will need rehabilitation sessions, with an average of four sessions per individual. This results in an estimated 2,000 sessions, budgeted at 18 JOD per session. Any underspend resulting from lower-than-expected utilization will be reallocated to the procurement of assistive devices to further support beneficiaries’ functional recovery. | N28: List of benificiraies, Registration sheet and sessions attendance sheets | O28: no reallocation without prior approval | P28: Agreed
A29: Prog_6 | B29: Gaza | C29: Axillary crutches – X-Large | D29: Piece | E29: 300 | F29: 1 | G29: JOD | H29: 20 | I29: 1 | J29: =I29*H29*F29*E29 -> 6000 | K29: =J29*1.23 -> 7380 | L29: =J29*1.41 -> 8460 | M29: Assistive devices are budgeted to support approximately 501 beneficiaries, with an estimated average cost of 229 JOD per case. These devices may include wheelchairs, crutches, portable toilet chairs, and medical beds. As needs differ across individuals, not all beneficiaries will receive the same items; distribution will be strictly based on clinical assessment and identified functional requirements. This budget line ensures that beneficiaries receive the most appropriate mobility and daily-living support devices to enhance independence and improve overall quality of life. | N29: Purchase Request, Purchase order, Goods Received note (GRN), and, Donation certificate | O29: The unit cost is too high and no need to buy medical bed, please review this part again and make sure it does not exceed 20,000 JD as a total | P29: The beds included under this project are standard (non-medical) beds, selected to meet beneficiaries’ daily living needs in a dignified manner. The unit costs of wheelchairs, standard beds, and toilet chairs exceed USD 20, reflecting current market prices, quality requirements, and availability constraints. Many beneficiaries will require more than one assistive device based on individual functional assessments. Providing multiple devices is essential to ensure safe mobility, continuity of care, and effective rehabilitation outcomes, and to uphold a dignified standard of assistance. In addition, RHS is providing tents for selected cases under separate projects as a complementary service, particularly for highly vulnerable households. This integrated approach allows the project to address both rehabilitation needs and basic living conditions, without duplicating costs within this budget.
A30: Prog_7 | B30: Gaza | C30: Active wheelchair - Regular | D30: Piece | E30: 200 | F30: 1 | G30: JOD | H30: 141 | I30: 1 | J30: =I30*H30*F30*E30 -> 28200 | K30: =J30*1.23 -> 34686 | L30: =J30*1.41 -> 39762
A31: Prog_8 | B31: Gaza | C31: Folding bed - with mattress | D31: Piece | E31: 96 | F31: 1 | G31: JOD | H31: 142 | I31: 1 | J31: =I31*H31*F31*E31 -> 13632 | K31: =J31*1.23 -> 16767.36 | L31: =J31*1.41 -> 19221.12
A32: Prog_9 | B32: Gaza | C32: Toilet chair | D32: Piece | E32: 300 | F32: 1 | G32: JOD | H32: 30 | I32: 1 | J32: =I32*H32*F32*E32 -> 9000 | K32: =J32*1.23 -> 11070 | L32: =J32*1.41 -> 12690
A33: Prog_10 | B33: Gaza | C33: Walking frame without wheel - adult | D33: Piece | E33: 200 | F33: 1 | G33: JOD | H33: 25 | I33: 1 | J33: =I33*H33*F33*E33 -> 5000 | K33: =J33*1.23 -> 6150 | L33: =J33*1.41 -> 7050
A34: Prog_11 | B34: Gaza | C34: Walking frame without wheel - child | D34: Piece | E34: 30 | F34: 1 | G34: JOD | H34: 25 | I34: 1 | J34: =I34*H34*F34*E34 -> 750 | K34: =J34*1.23 -> 922.5 | L34: =J34*1.41 -> 1057.5
A35: Prog_12 | B35: Gaza | C35: Elbow crutch | D35: Piece | E35: 200 | F35: 1 | G35: JOD | H35: 20 | I35: 1 | J35: =I35*H35*F35*E35 -> 4000 | K35: =J35*1.23 -> 4920 | L35: =J35*1.41 -> 5640
A36: Prog_13 | B36: Gaza | C36: Medical shoes for the prosthesis | D36: Piece | E36: 600 | F36: 1 | G36: JOD | H36: 10.7 | I36: 1 | J36: =I36*H36*F36*E36 -> 6420 | K36: =J36*1.23 -> 7896.6 | L36: =J36*1.41 -> 9052.2
A37: Prog_14 | B37: Gaza | C37: crutches Tips | D37: Piece | E37: 600 | F37: 1 | G37: JOD | H37: 3.55 | I37: 1 | J37: =I37*H37*F37*E37 -> 2130 | K37: =J37*1.23 -> 2619.9 | L37: =J37*1.41 -> 3003.3
A38: Prog_5 | B38: Gaza | C38: Visability | D38: Lum | E38: 1 | F38: 1 | G38: JOD | H38: 11810 | I38: 1 | J38: 11810 | K38: =J38*1.23 -> 14526.3 | L38: =J38*1.41 -> 16652.1 | M38: This budget line covers visibility and documentation requirements for the intervention, ensuring full compliance with donor branding guidelines. A minimum of 40 branded video stories will be produced and shared with Qatar Charity, in addition to over 200 high-quality photographs capturing and documenting as 200 beneficiary. These materials will support transparent reporting, highlight project impact, and enhance donor visibility.” Cost calculations Videos 250(Cost per video)*40 (Number of Videos)= 10,000 USD (Total) Photography & Documentation (200 Individuals): A dedicated photographer will document an average of 3 beneficiary cases per day over 66 working days, totaling 200 individuals. The daily rate is USD 80, resulting in a total cost of USD 5,280. 10 roll-ups cost per roll-up is 120USD. Total 1,200 USD 2 panners cost per 1 is 45 USD, total 90 USD Grand Total 10,000 + 5,280 +1200 + 90 = 16,570 | N38: Videos and Photos | O38: too high allocated for this budget line, please revise this | P38: Cost amended and calculation added Cost calculations Videos 250(Cost per video)*40 (Number of Videos)= 10,000 USD (Total) Photography & Documentation (200 Individuals): A dedicated photographer will document an average of 3 beneficiary cases per day over 66 working days, totaling 200 individuals. The daily rate is USD 80, resulting in a total cost of USD 5,280. 10 roll-ups cost per roll-up is 120USD. Total 1,200 USD 2 panners cost per 1 is 45 USD, total 90 USD Grand Total 10,000 + 5,280 +1200 + 90 = 16,570
A39: Total Office and Utilities | J39: =SUM(J26:J38) -> 653314.9 | K39: =SUM(K26:K38) -> 803577.33 | L39: =SUM(L26:L38) -> 921174.01
A40: Grand Total | J40: =SUM(J39,J24,J18) -> 653314.9 | K40: =SUM(K39,K24,K18) -> 803577.33 | L40: =SUM(L39,L24,L18) -> 921174.01

Sheet Sheet1
D1: Restoring Hope - Project Budget
A2: Project Code | B2: RH-2025-0006 | C2: Date of Submission: 14th of Nov 2025 | I2: Total Project Budget | J2: 921200 | K2: USD
A3: Donor | B3: Qatar Charity | C3: Project Duration 12 Months | I3: Remaining Budget | J3: =J2-L47 -> 25.991 | K3: USD
A4: Budget Line | B4: Location | C4: Description | D4: UNIT | E4: # of Unit | F4: Freq | G4: curr | H4: unit price | I4: Covering percentage from this project | J4: Total | K4: Total in Euro | L4: Total in USD | M4: Total Amount | N4: Actual | O4: Remaining | P4: Burn Rate | Q4: Forcast | R4: Commitments | S4: Actual with Commitments and Forcast | T4: Remaining with commitments and Forcast | U4: Burn Rate with Commitments | V4: Month
V5: Dec | W5: Jan | X5: Feb | Y5: Mar | Z5: Apr | AA5: May | AB5: Jun | AC5: Jul | AD5: Aug | AE5: Sep | AF5: Oct | AG5: Nov | AH5: Dec | AI5: Jan | AJ5: Feb | AK5: Mar | AL5: Apr
A6: SAL_8 | B6: Amm | C6: Program Director | D6: Months | E6: 1 | F6: 12 | G6: JOD | H6: 3500 | I6: 0 | J6: =E6*F6*H6*I6 -> 0 | K6: =J6*1.23 -> 0 | L6: =J6*1.41 -> 0 | M6: =[1]BUDGET!N6 -> Start Date | O6: =M6-N6 -> #VALUE! | P6: =N6/M6 -> #VALUE! | Q6: =SUM(V6:AL6) -> 0 | S6: =N6+Q6+R6 -> 0 | T6: =M6-S6 -> #VALUE! | U6: =S6/M6 -> #VALUE!
A7: SAL_9 | B7: Gaza | C7: Project Manager (GAZA) | D7: Months | E7: 1 | F7: 12 | G7: JOD | H7: 2100 | I7: 0 | J7: =E7*F7*H7*I7 -> 0 | K7: =J7*1.23 -> 0 | L7: =J7*1.41 -> 0 | M7: =[1]BUDGET!N7 -> 0 | O7: =M7-N7 -> 0 | P7: =N7/M7 -> #DIV/0! | Q7: =SUM(V7:AL7) -> 0 | S7: =N7+Q7+R7 -> 0 | T7: =M7-S7 -> 0 | U7: =S7/M7 -> #DIV/0!
A8: SAL_10 | B8: Amm | C8: MEAL Team Leader | D8: Months | E8: 1 | F8: 12 | G8: JOD | H8: 1200 | I8: 0 | J8: =E8*F8*H8*I8 -> 0 | K8: =J8*1.23 -> 0 | L8: =J8*1.41 -> 0 | M8: =[1]BUDGET!N8 -> Milestone 4 | O8: =M8-N8 -> #VALUE! | P8: =N8/M8 -> #VALUE! | Q8: =SUM(V8:AL8) -> 0 | S8: =N8+Q8+R8 -> 0 | T8: =M8-S8 -> #VALUE! | U8: =S8/M8 -> #VALUE!
A9: SAL_11 | B9: Gaza | C9: Gaza Technical Officer | D9: Months | E9: 1 | F9: 12 | G9: JOD | H9: 700 | I9: 0 | J9: =E9*F9*H9*I9 -> 0 | K9: =J9*1.23 -> 0 | L9: =J9*1.41 -> 0 | M9: =[1]BUDGET!N9 -> 0 | O9: =M9-N9 -> 0 | P9: =N9/M9 -> #DIV/0! | Q9: =SUM(V9:AL9) -> 0 | S9: =N9+Q9+R9 -> 0 | T9: =M9-S9 -> 0 | U9: =S9/M9 -> #DIV/0!
A10: SAL_12 | B10: Gaza | C10: Gaza Technical Officer | D10: Months | E10: 1 | F10: 12 | G10: JOD | H10: 700 | I10: 0 | J10: =E10*F10*H10*I10 -> 0 | K10: =J10*1.23 -> 0 | L10: =J10*1.41 -> 0 | M10: =[1]BUDGET!N10 -> 0 | O10: =M10-N10 -> 0 | P10: =N10/M10 -> #DIV/0! | Q10: =SUM(V10:AL10) -> 0 | S10: =N10+Q10+R10 -> 0 | T10: =M10-S10 -> 0 | U10: =S10/M10 -> #DIV/0!
A11: SAL_13 | B11: Amm | C11: Amman Technical Officer | D11: Months | E11: 1 | F11: 12 | G11: JOD | H11: 1500 | I11: 0 | J11: =E11*F11*H11*I11 -> 0 | K11: =J11*1.23 -> 0 | L11: =J11*1.41 -> 0 | M11: =[1]BUDGET!N11 -> 0 | O11: =M11-N11 -> 0 | P11: =N11/M11 -> #DIV/0! | Q11: =SUM(V11:AL11) -> 0 | S11: =N11+Q11+R11 -> 0 | T11: =M11-S11 -> 0 | U11: =S11/M11 -> #DIV/0!
A12: SAL_16 | B12: Amm | C12: Finance and Support Function Manager | D12: Months | E12: 1 | F12: 12 | G12: JOD | H12: 3500 | I12: 0 | J12: =E12*F12*H12*I12 -> 0 | K12: =J12*1.23 -> 0 | L12: =J12*1.41 -> 0 | M12: =[1]BUDGET!N12 -> 0 | O12: =M12-N12 -> 0 | P12: =N12/M12 -> #DIV/0! | Q12: =SUM(V12:AL12) -> 0 | S12: =N12+Q12+R12 -> 0 | T12: =M12-S12 -> 0 | U12: =S12/M12 -> #DIV/0!
A13: SAL_17 | B13: Amm | C13: Supply Chain Officer | D13: Months | E13: 1 | F13: 12 | G13: JOD | H13: 550 | I13: 0 | J13: =E13*F13*H13*I13 -> 0 | K13: =J13*1.23 -> 0 | L13: =J13*1.41 -> 0 | M13: =[1]BUDGET!N13 -> 0 | O13: =M13-N13 -> 0 | P13: =N13/M13 -> #DIV/0! | Q13: =SUM(V13:AL13) -> 0 | S13: =N13+Q13+R13 -> 0 | T13: =M13-S13 -> 0 | U13: =S13/M13 -> #DIV/0!
A14: SAL_18 | B14: Amm | C14: Driver | D14: Months | E14: 1 | F14: 12 | G14: JOD | H14: 300 | I14: 0 | J14: =E14*F14*H14*I14 -> 0 | K14: =J14*1.23 -> 0 | L14: =J14*1.41 -> 0 | M14: =[1]BUDGET!N14 -> 0 | O14: =M14-N14 -> 0 | P14: =N14/M14 -> #DIV/0! | Q14: =SUM(V14:AL14) -> 0 | S14: =N14+Q14+R14 -> 0 | T14: =M14-S14 -> 0 | U14: =S14/M14 -> #DIV/0!
A15: SAL_19 | B15: Amm | C15: Admin Staff | D15: Months | E15: 1 | F15: 12 | G15: JOD | H15: 900 | I15: 0 | J15: =E15*F15*H15*I15 -> 0 | K15: =J15*1.23 -> 0 | L15: =J15*1.41 -> 0 | M15: =[1]BUDGET!N15 -> 0 | O15: =M15-N15 -> 0 | P15: =N15/M15 -> #DIV/0! | Q15: =SUM(V15:AL15) -> 0 | S15: =N15+Q15+R15 -> 0 | T15: =M15-S15 -> 0 | U15: =S15/M15 -> #DIV/0!
A16: SAL_22 | B16: Amm | C16: Health Insurance | D16: Lum | E16: 1 | F16: 1 | G16: JOD | H16: 10000 | I16: 0 | J16: =E16*F16*H16*I16 -> 0 | K16: =J16*1.23 -> 0 | L16: =J16*1.41 -> 0 | M16: =[1]BUDGET!N16 -> 0 | O16: =M16-N16 -> 0 | P16: =N16/M16 -> #DIV/0! | Q16: =SUM(V16:AL16) -> 0 | S16: =N16+Q16+R16 -> 0 | T16: =M16-S16 -> 0 | U16: =S16/M16 -> #DIV/0!
A17: SAL_23 | B17: Amm | C17: Social Security | D17: Lum | E17: 1 | F17: 1 | G17: JOD | H17: 25000 | I17: 0 | J17: =E17*F17*H17*I17 -> 0 | K17: =J17*1.23 -> 0 | L17: =J17*1.41 -> 0 | M17: =[1]BUDGET!N17 -> 0 | O17: =M17-N17 -> 0 | P17: =N17/M17 -> #DIV/0! | Q17: =SUM(V17:AL17) -> 0 | S17: =N17+Q17+R17 -> 0 | T17: =M17-S17 -> 0 | U17: =S17/M17 -> #DIV/0!
A18: Total Personel | J18: =SUM(J6:J17) -> 0 | K18: =J18*1.23 -> 0 | L18: =J18*1.41 -> 0 | M18: =[1]BUDGET!N18 -> 0 | N18: =SUM(N6:N17) -> 0 | O18: =M18-N18 -> 0 | P18: =N18/M18 -> #DIV/0! | Q18: =SUM(V18:AL18) -> 0 | S18: =N18+Q18+R18 -> 0 | T18: =M18-S18 -> 0 | U18: =S18/M18 -> #DIV/0!
A19: Office and Utilities Cost | M19: =[1]BUDGET!N19 -> 0 | O19: =M19-N19 -> 0 | P19: =N19/M19 -> #DIV/0! | Q19: =SUM(V19:AL19) -> 0 | S19: =N19+Q19+R19 -> 0 | T19: =M19-S19 -> 0 | U19: =S19/M19 -> #DIV/0!
A20: OFC001 | B20: Amm | C20: Office Rent Cost | D20: Months | E20: 12 | F20: 1 | G20: JOD | H20: 2500 | I20: 0 | J20: =I20*H20*F20*E20 -> 0 | K20: =J20*1.23 -> 0 | L20: =J20*1.41 -> 0 | M20: =[1]BUDGET!N20 -> 0 | O20: =M20-N20 -> 0 | P20: =N20/M20 -> #DIV/0! | Q20: =SUM(V20:AL20) -> 0 | S20: =N20+Q20+R20 -> 0 | T20: =M20-S20 -> 0 | U20: =S20/M20 -> #DIV/0!
A21: EQP001 | B21: Amm | C21: IT Equipment | D21: Units | E21: 4 | F21: 1 | G21: JOD | H21: 700 | I21: 0 | J21: =I21*H21*F21*E21 -> 0 | K21: =J21*1.23 -> 0 | L21: =J21*1.41 -> 0 | M21: =[1]BUDGET!N21 -> 0 | O21: =M21-N21 -> 0 | P21: =N21/M21 -> #DIV/0! | Q21: =SUM(V21:AL21) -> 0 | S21: =N21+Q21+R21 -> 0 | T21: =M21-S21 -> 0 | U21: =S21/M21 -> #DIV/0!
A22: EQP002 | B22: Gaza | C22: Field Equipment | D22: Units | E22: 3 | F22: 1 | G22: JOD | H22: 700 | I22: 0 | J22: =I22*H22*F22*E22 -> 0 | K22: =J22*1.23 -> 0 | L22: =J22*1.41 -> 0 | M22: =[1]BUDGET!N22 -> 0 | O22: =M22-N22 -> 0 | P22: =N22/M22 -> #DIV/0! | Q22: =SUM(V22:AL22) -> 0 | S22: =N22+Q22+R22 -> 0 | T22: =M22-S22 -> 0 | U22: =S22/M22 -> #DIV/0!
A23: EQP003 | B23: Amm and Gaza | C23: Visability | D23: Lum | E23: 1 | F23: 1 | G23: JOD | H23: 5000 | I23: 0 | J23: =I23*H23*F23*E23 -> 0 | K23: =J23*1.23 -> 0 | L23: =J23*1.41 -> 0 | M23: =[1]BUDGET!N23 -> 0 | O23: =M23-N23 -> 0 | P23: =N23/M23 -> #DIV/0! | Q23: =SUM(V23:AL23) -> 0 | S23: =N23+Q23+R23 -> 0 | T23: =M23-S23 -> 0 | U23: =S23/M23 -> #DIV/0!
A24: Total Office and Utilities | J24: =SUM(J20:J23) -> 0 | K24: =SUM(K20:K23) -> 0 | L24: =SUM(L20:L23) -> 0 | M24: =[1]BUDGET!N24 -> 0 | N24: =SUM(N20:N23) -> 0 | O24: =M24-N24 -> 0 | P24: =N24/M24 -> #DIV/0! | Q24: =SUM(V24:AL24) -> 0 | S24: =N24+Q24+R24 -> 0 | T24: =M24-S24 -> 0 | U24: =S24/M24 -> #DIV/0!
A25: Personel | M25: =[1]BUDGET!N25 -> 0 | O25: =M25-N25 -> 0 | P25: =N25/M25 -> #DIV/0! | Q25: =SUM(V25:AL25) -> 0 | S25: =N25+Q25+R25 -> 0 | T25: =M25-S25 -> 0 | U25: =S25/M25 -> #DIV/0!
A26: Prog_1 | B26: Gaza | C26: Prosthetics Cost | D26: Lum | E26: 1 | F26: 1 | G26: JOD | H26: =446550.9+47822 -> 494372.9 | I26: 1 | J26: =I26*H26*F26*E26 -> 494372.9 | K26: =J26*1.23 -> 608078.67 | L26: =J26*1.41 -> 697065.79 | M26: =L26 -> 697065.79 | N26: =(SUMIFS('Expense Allocation'!$J$8:$J$157,'Expense Allocation'!$F$8:$F$157,$A26)+SUMIFS('Expense Allocation'!$K$8:$K$157,'Expense Allocation'!$H$8:$H$157,$A26))*'Expense Allocation'!$B$3 -> 706058.22 | O26: =M26-N26 -> -8992.4287 | P26: =N26/M26 -> 1.0129004 | Q26: =SUM(V26:AL26) -> 0 | S26: =N26+Q26+R26 -> 706058.22 | T26: =M26-S26 -> -8992.4287 | U26: =S26/M26 -> 1.0129004
A27: Prog_2 | B27: Gaza | C27: Mental Helth Sessions Cost | D27: Session | E27: 2000 | F27: 1 | G27: JOD | H27: 18 | I27: 1 | J27: =I27*H27*F27*E27 -> 36000 | K27: =J27*1.23 -> 44280 | L27: =J27*1.41 -> 50760 | M27: =L27 -> 50760 | N27: =(SUMIFS('Expense Allocation'!$J$8:$J$157,'Expense Allocation'!$F$8:$F$157,$A27)+SUMIFS('Expense Allocation'!$K$8:$K$157,'Expense Allocation'!$H$8:$H$157,$A27))*'Expense Allocation'!$B$3 -> 48242.922 | O27: =M27-N27 -> 2517.0784 | P27: =N27/M27 -> 0.95041217 | Q27: =SUM(V27:AL27) -> 0 | S27: =N27+Q27+R27 -> 48242.922 | T27: =M27-S27 -> 2517.0784 | U27: =S27/M27 -> 0.95041217
A28: Prog_3 | B28: Gaza | C28: Physical rehabilitation Sessions Cost | D28: Session | E28: 2000 | F28: 1 | G28: JOD | H28: 18 | I28: 1 | J28: =I28*H28*F28*E28 -> 36000 | K28: =J28*1.23 -> 44280 | L28: =J28*1.41 -> 50760 | M28: =L28 -> 50760 | N28: =(SUMIFS('Expense Allocation'!$J$8:$J$157,'Expense Allocation'!$F$8:$F$157,$A28)+SUMIFS('Expense Allocation'!$K$8:$K$157,'Expense Allocation'!$H$8:$H$157,$A28))*'Expense Allocation'!$B$3 -> 42757.878 | O28: =M28-N28 -> 8002.1222 | P28: =N28/M28 -> 0.84235378 | Q28: =SUM(V28:AL28) -> 0 | S28: =N28+Q28+R28 -> 42757.878 | T28: =M28-S28 -> 8002.1222 | U28: =S28/M28 -> 0.84235378
A29: Prog_6 | B29: Gaza | C29: Axillary crutches – X-Large | D29: Piece | E29: 300 | F29: 1 | G29: JOD | H29: 20 | I29: 1 | J29: =I29*H29*F29*E29 -> 6000 | K29: =J29*1.23 -> 7380 | L29: =J29*1.41 -> 8460 | M29: =L29 -> 8460 | N29: =(SUMIFS('Expense Allocation'!$J$8:$J$157,'Expense Allocation'!$F$8:$F$157,$A29)+SUMIFS('Expense Allocation'!$K$8:$K$157,'Expense Allocation'!$H$8:$H$157,$A29))*'Expense Allocation'!$B$3 -> 0 | O29: =M29-N29 -> 8460 | P29: =N29/M29 -> 0 | Q29: =SUM(V29:AL29) -> 0 | S29: =N29+Q29+R29 -> 0 | T29: =M29-S29 -> 8460 | U29: =S29/M29 -> 0
A30: Prog_7 | B30: Gaza | C30: Active wheelchair - Regular | D30: Piece | E30: 200 | F30: 1 | G30: JOD | H30: 141 | I30: 1 | J30: =I30*H30*F30*E30 -> 28200 | K30: =J30*1.23 -> 34686 | L30: =J30*1.41 -> 39762 | M30: =L30 -> 39762 | N30: =(SUMIFS('Expense Allocation'!$J$8:$J$157,'Expense Allocation'!$F$8:$F$157,$A30)+SUMIFS('Expense Allocation'!$K$8:$K$157,'Expense Allocation'!$H$8:$H$157,$A30))*'Expense Allocation'!$B$3 -> 0 | O30: =M30-N30 -> 39762 | P30: =N30/M30 -> 0 | Q30: =SUM(V30:AL30) -> 0 | S30: =N30+Q30+R30 -> 0 | T30: =M30-S30 -> 39762 | U30: =S30/M30 -> 0
A31: Prog_8 | B31: Gaza | C31: Folding bed - with mattress | D31: Piece | E31: 96 | F31: 1 | G31: JOD | H31: 142 | I31: 1 | J31: =I31*H31*F31*E31 -> 13632 | K31: =J31*1.23 -> 16767.36 | L31: =J31*1.41 -> 19221.12 | M31: =L31 -> 19221.12 | N31: =(SUMIFS('Expense Allocation'!$J$8:$J$157,'Expense Allocation'!$F$8:$F$157,$A31)+SUMIFS('Expense Allocation'!$K$8:$K$157,'Expense Allocation'!$H$8:$H$157,$A31))*'Expense Allocation'!$B$3 -> 0 | O31: =M31-N31 -> 19221.12 | P31: =N31/M31 -> 0 | Q31: =SUM(V31:AL31) -> 0 | S31: =N31+Q31+R31 -> 0 | T31: =M31-S31 -> 19221.12 | U31: =S31/M31 -> 0
A32: Prog_9 | B32: Gaza | C32: Toilet chair | D32: Piece | E32: 300 | F32: 1 | G32: JOD | H32: 30 | I32: 1 | J32: =I32*H32*F32*E32 -> 9000 | K32: =J32*1.23 -> 11070 | L32: =J32*1.41 -> 12690 | M32: =L32 -> 12690 | N32: =(SUMIFS('Expense Allocation'!$J$8:$J$157,'Expense Allocation'!$F$8:$F$157,$A32)+SUMIFS('Expense Allocation'!$K$8:$K$157,'Expense Allocation'!$H$8:$H$157,$A32))*'Expense Allocation'!$B$3 -> 0 | O32: =M32-N32 -> 12690 | P32: =N32/M32 -> 0 | Q32: =SUM(V32:AL32) -> 0 | S32: =N32+Q32+R32 -> 0 | T32: =M32-S32 -> 12690 | U32: =S32/M32 -> 0
A33: Prog_10 | B33: Gaza | C33: Walking frame without wheel - adult | D33: Piece | E33: 200 | F33: 1 | G33: JOD | H33: 25 | I33: 1 | J33: =I33*H33*F33*E33 -> 5000 | K33: =J33*1.23 -> 6150 | L33: =J33*1.41 -> 7050 | M33: =L33 -> 7050 | N33: =(SUMIFS('Expense Allocation'!$J$8:$J$157,'Expense Allocation'!$F$8:$F$157,$A33)+SUMIFS('Expense Allocation'!$K$8:$K$157,'Expense Allocation'!$H$8:$H$157,$A33))*'Expense Allocation'!$B$3 -> 0 | O33: =M33-N33 -> 7050 | P33: =N33/M33 -> 0 | Q33: =SUM(V33:AL33) -> 0 | S33: =N33+Q33+R33 -> 0 | T33: =M33-S33 -> 7050 | U33: =S33/M33 -> 0
A34: Prog_11 | B34: Gaza | C34: Walking frame without wheel - child | D34: Piece | E34: 30 | F34: 1 | G34: JOD | H34: 25 | I34: 1 | J34: =I34*H34*F34*E34 -> 750 | K34: =J34*1.23 -> 922.5 | L34: =J34*1.41 -> 1057.5 | M34: =L34 -> 1057.5 | N34: =(SUMIFS('Expense Allocation'!$J$8:$J$157,'Expense Allocation'!$F$8:$F$157,$A34)+SUMIFS('Expense Allocation'!$K$8:$K$157,'Expense Allocation'!$H$8:$H$157,$A34))*'Expense Allocation'!$B$3 -> 0 | O34: =M34-N34 -> 1057.5 | P34: =N34/M34 -> 0 | Q34: =SUM(V34:AL34) -> 0 | S34: =N34+Q34+R34 -> 0 | T34: =M34-S34 -> 1057.5 | U34: =S34/M34 -> 0
A35: Prog_12 | B35: Gaza | C35: Elbow crutch | D35: Piece | E35: 200 | F35: 1 | G35: JOD | H35: 20 | I35: 1 | J35: =I35*H35*F35*E35 -> 4000 | K35: =J35*1.23 -> 4920 | L35: =J35*1.41 -> 5640 | M35: =L35 -> 5640 | N35: =(SUMIFS('Expense Allocation'!$J$8:$J$157,'Expense Allocation'!$F$8:$F$157,$A35)+SUMIFS('Expense Allocation'!$K$8:$K$157,'Expense Allocation'!$H$8:$H$157,$A35))*'Expense Allocation'!$B$3 -> 0 | O35: =M35-N35 -> 5640 | P35: =N35/M35 -> 0 | Q35: =SUM(V35:AL35) -> 0 | S35: =N35+Q35+R35 -> 0 | T35: =M35-S35 -> 5640 | U35: =S35/M35 -> 0
A36: Prog_13 | B36: Gaza | C36: Medical shoes for the prosthesis | D36: Piece | E36: 600 | F36: 1 | G36: JOD | H36: 10.7 | I36: 1 | J36: =I36*H36*F36*E36 -> 6420 | K36: =J36*1.23 -> 7896.6 | L36: =J36*1.41 -> 9052.2 | M36: =L36 -> 9052.2 | N36: =(SUMIFS('Expense Allocation'!$J$8:$J$157,'Expense Allocation'!$F$8:$F$157,$A36)+SUMIFS('Expense Allocation'!$K$8:$K$157,'Expense Allocation'!$H$8:$H$157,$A36))*'Expense Allocation'!$B$3 -> 0 | O36: =M36-N36 -> 9052.2 | P36: =N36/M36 -> 0 | Q36: =SUM(V36:AL36) -> 0 | S36: =N36+Q36+R36 -> 0 | T36: =M36-S36 -> 9052.2 | U36: =S36/M36 -> 0
A37: Prog_14 | B37: Gaza | C37: crutches Tips | D37: Piece | E37: 600 | F37: 1 | G37: JOD | H37: 3.55 | I37: 1 | J37: =I37*H37*F37*E37 -> 2130 | K37: =J37*1.23 -> 2619.9 | L37: =J37*1.41 -> 3003.3 | M37: =L37 -> 3003.3 | N37: =(SUMIFS('Expense Allocation'!$J$8:$J$157,'Expense Allocation'!$F$8:$F$157,$A37)+SUMIFS('Expense Allocation'!$K$8:$K$157,'Expense Allocation'!$H$8:$H$157,$A37))*'Expense Allocation'!$B$3 -> 0 | O37: =M37-N37 -> 3003.3 | P37: =N37/M37 -> 0 | Q37: =SUM(V37:AL37) -> 0 | S37: =N37+Q37+R37 -> 0 | T37: =M37-S37 -> 3003.3 | U37: =S37/M37 -> 0
A38: Prog_5 | B38: Gaza | C38: Visability | D38: Lum | E38: 1 | F38: 1 | G38: JOD | H38: 11810 | I38: 1 | J38: 11810 | K38: =J38*1.23 -> 14526.3 | L38: =J38*1.41 -> 16652.1 | M38: =L38 -> 16652.1 | N38: =(SUMIFS('Expense Allocation'!$J$8:$J$157,'Expense Allocation'!$F$8:$F$157,$A38)+SUMIFS('Expense Allocation'!$K$8:$K$157,'Expense Allocation'!$H$8:$H$157,$A38))*'Expense Allocation'!$B$3 -> 17773.792 | O38: =M38-N38 -> -1121.6917 | P38: =N38/M38 -> 1.0673604 | Q38: =SUM(V38:AL38) -> 0 | S38: =N38+Q38+R38 -> 17773.792 | T38: =M38-S38 -> -1121.6917 | U38: =S38/M38 -> 1.0673604
A39: Unbudgeted Expenses (not in approved budget)
A40: UNB_1 | B40: Amm and Gaza | C40: Patient & Staff Transportation | D40: Lum | G40: JOD | J40: =I40*H40*F40*E40 -> 0 | K40: =J40*1.23 -> 0 | L40: =J40*1.41 -> 0 | M40: =L40 -> 0 | N40: =(SUMIFS('Expense Allocation'!$J$8:$J$157,'Expense Allocation'!$F$8:$F$157,$A40)+SUMIFS('Expense Allocation'!$K$8:$K$157,'Expense Allocation'!$H$8:$H$157,$A40))*'Expense Allocation'!$B$3 -> 52067.021 | O40: =M40-N40 -> -52067.021 | P40: =IF(M40=0,"Unbudgeted",N40/M40) -> Unbudgeted | Q40: =SUM(V40:AL40) -> 0 | S40: =N40+Q40+R40 -> 52067.021 | T40: =M40-S40 -> -52067.021 | U40: =IF(M40=0,"Unbudgeted",S40/M40) -> Unbudgeted
A41: UNB_2 | B41: Amm | C41: Medical Services (Surgery, Hospital, Lab Tests) | D41: Lum | G41: JOD | J41: =I41*H41*F41*E41 -> 0 | K41: =J41*1.23 -> 0 | L41: =J41*1.41 -> 0 | M41: =L41 -> 0 | N41: =(SUMIFS('Expense Allocation'!$J$8:$J$157,'Expense Allocation'!$F$8:$F$157,$A41)+SUMIFS('Expense Allocation'!$K$8:$K$157,'Expense Allocation'!$H$8:$H$157,$A41))*'Expense Allocation'!$B$3 -> 16399.484 | O41: =M41-N41 -> -16399.484 | P41: =IF(M41=0,"Unbudgeted",N41/M41) -> Unbudgeted | Q41: =SUM(V41:AL41) -> 0 | S41: =N41+Q41+R41 -> 16399.484 | T41: =M41-S41 -> -16399.484 | U41: =IF(M41=0,"Unbudgeted",S41/M41) -> Unbudgeted
A42: UNB_3 | B42: Gaza | C42: Shopping Vouchers (incl. distribution fee) | D42: Lum | G42: JOD | J42: =I42*H42*F42*E42 -> 0 | K42: =J42*1.23 -> 0 | L42: =J42*1.41 -> 0 | M42: =L42 -> 0 | N42: =(SUMIFS('Expense Allocation'!$J$8:$J$157,'Expense Allocation'!$F$8:$F$157,$A42)+SUMIFS('Expense Allocation'!$K$8:$K$157,'Expense Allocation'!$H$8:$H$157,$A42))*'Expense Allocation'!$B$3 -> 8712.3491 | O42: =M42-N42 -> -8712.3491 | P42: =IF(M42=0,"Unbudgeted",N42/M42) -> Unbudgeted | Q42: =SUM(V42:AL42) -> 0 | S42: =N42+Q42+R42 -> 8712.3491 | T42: =M42-S42 -> -8712.3491 | U42: =IF(M42=0,"Unbudgeted",S42/M42) -> Unbudgeted
A43: UNB_4 | B43: Amm | C43: Patient Activities, Events & Meals | D43: Lum | G43: JOD | J43: =I43*H43*F43*E43 -> 0 | K43: =J43*1.23 -> 0 | L43: =J43*1.41 -> 0 | M43: =L43 -> 0 | N43: =(SUMIFS('Expense Allocation'!$J$8:$J$157,'Expense Allocation'!$F$8:$F$157,$A43)+SUMIFS('Expense Allocation'!$K$8:$K$157,'Expense Allocation'!$H$8:$H$157,$A43))*'Expense Allocation'!$B$3 -> 3094.0476 | O43: =M43-N43 -> -3094.0476 | P43: =IF(M43=0,"Unbudgeted",N43/M43) -> Unbudgeted | Q43: =SUM(V43:AL43) -> 0 | S43: =N43+Q43+R43 -> 3094.0476 | T43: =M43-S43 -> -3094.0476 | U43: =IF(M43=0,"Unbudgeted",S43/M43) -> Unbudgeted
A44: UNB_5 | B44: — | C44: Other – To Be Reclassified | D44: Lum | G44: JOD | J44: =I44*H44*F44*E44 -> 0 | K44: =J44*1.23 -> 0 | L44: =J44*1.41 -> 0 | M44: =L44 -> 0 | N44: =(SUMIFS('Expense Allocation'!$J$8:$J$157,'Expense Allocation'!$F$8:$F$157,$A44)+SUMIFS('Expense Allocation'!$K$8:$K$157,'Expense Allocation'!$H$8:$H$157,$A44))*'Expense Allocation'!$B$3 -> 70.5 | O44: =M44-N44 -> -70.5 | P44: =IF(M44=0,"Unbudgeted",N44/M44) -> Unbudgeted | Q44: =SUM(V44:AL44) -> 0 | S44: =N44+Q44+R44 -> 70.5 | T44: =M44-S44 -> -70.5 | U44: =IF(M44=0,"Unbudgeted",S44/M44) -> Unbudgeted
A45: Total Unbudgeted Expenses | J45: =SUM(J40:J44) -> 0 | K45: =SUM(K40:K44) -> 0 | L45: =SUM(L40:L44) -> 0 | M45: =SUM(M40:M44) -> 0 | N45: =SUM(N40:N44) -> 80343.402 | O45: =M45-N45 -> -80343.402 | P45: =IF(M45=0,"Unbudgeted",N45/M45) -> Unbudgeted | Q45: =SUM(V45:AL45) -> 0 | S45: =N45+Q45+R45 -> 80343.402 | T45: =M45-S45 -> -80343.402 | U45: =IF(M45=0,"Unbudgeted",S45/M45) -> Unbudgeted
A46: Total Office and Utilities | J46: =SUM(J26:J38) -> 653314.9 | K46: =SUM(K26:K38) -> 803577.33 | L46: =SUM(L26:L38) -> 921174.01 | M46: =L46 -> 921174.01 | N46: =SUM(N26:N38) -> 814832.81 | O46: =M46-N46 -> 106341.2 | P46: =N46/M46 -> 0.88455905 | Q46: =SUM(V46:AL46) -> 0 | S46: =N46+Q46+R46 -> 814832.81 | T46: =M46-S46 -> 106341.2 | U46: =S46/M46 -> 0.88455905
A47: Grand Total | J47: =SUM(J46,J45,J24,J18) -> 653314.9 | K47: =SUM(K46,K45,K24,K18) -> 803577.33 | L47: =SUM(L46,L45,L24,L18) -> 921174.01 | M47: =L47 -> 921174.01 | N47: =SUM(N46,N45,N24,N18) -> 895176.21 | O47: =M47-N47 -> 25997.799 | P47: =N47/M47 -> 0.97177754 | Q47: =SUM(V47:AL47) -> 0 | S47: =N47+Q47+R47 -> 895176.21 | T47: =M47-S47 -> 25997.799 | U47: =S47/M47 -> 0.97177754
C49: Financial Summary | J49: JOD | L49: USD
C50: Donation received from Qatar Charity | J50: 652209.6 | L50: =J50*'Expense Allocation'!$B$3 -> 919615.54
C51: Approved budget | J51: =L51/'Expense Allocation'!$B$3 -> 653314.9 | L51: =M47 -> 921174.01
C52: Spent on approved budget lines | J52: =L52/'Expense Allocation'!$B$3 -> 577895.61 | L52: =SUM(N46,N24,N18) -> 814832.81
C53: Spent on unbudgeted lines | J53: =L53/'Expense Allocation'!$B$3 -> 56981.136 | L53: =N45 -> 80343.402
C54: Total spent | J54: =L54/'Expense Allocation'!$B$3 -> 634876.74 | L54: =N47 -> 895176.21
C55: Remaining approved budget (after all spending) | J55: =L55/'Expense Allocation'!$B$3 -> 18438.155 | L55: =L51-L54 -> 25997.799
C56: Cash balance (donation received – total spent) | J56: =J50-J54 -> 17332.855 | L56: =L50-L54 -> 24439.326
C57: Overall burn rate vs approved budget | L57: =L54/L51 -> 0.97177754

Sheet Expense Allocation
A1: Expense Allocation – Qatar Charity Project (RH-2025-0006)
A2: GL period 01/01/2025 – 09/30/2026. Amounts in JOD; converted to USD on Sheet1 Actual column. Change Budget Line / % cells to re-allocate.
A3: JOD → USD rate | B3: 1.41 | D3: Total expenses in ledger (JOD) | E3: =SUM(E8:E157) -> 634876.74
A4: Total per Trial Balance (JOD) | B4: 634876.74 | D4: Allocated to budget lines (JOD) | E4: =SUM(J8:K157) -> 634876.75
D5: Unallocated (JOD) | E5: =ROUND(E3-E4,3) -> 0
D6: Check vs Trial Balance (should be 0) | E6: =E3-B4 -> 0
A7: Account Code | B7: Account Name | C7: Date | D7: Description | E7: Amount (JOD) | F7: Budget Line 1 | G7: % Line 1 | H7: Budget Line 2 | I7: % Line 2 | J7: Line 1 Amount (JOD) | K7: Line 2 Amount (JOD) | L7: Allocation Note
A8: 601008 | B8: Advertising & Digital Services | C8: 46058 | D8: MISC/2026/02/0003 (Donations – Gaza families (Cochlear Implant Project)) Job advertisement - LinkedIn - Date 2026/01/23 - Job Title Partnership officer | E8: 35 | F8: UNB_5 | G8: 1 | I8: 0 | J8: =E8*G8 -> 35 | K8: =E8*I8 -> 0 | L8: Unbudgeted – To be reclassified (miscoded job ad / unspecified assistive device)
A9: 601008 | B9: Advertising & Digital Services | C9: 46097 | D9: MISC/2026/03/0010 (Cheq No 82 - Name Nader Emad AL-Deen - Dated 2026/03/12) Documentary video production services for organizational [...] | E9: 5310 | F9: Prog_5 | G9: 1 | I9: 0 | J9: =E9*G9 -> 5310 | K9: =E9*I9 -> 0
A10: 601008 | B10: Advertising & Digital Services | C10: 46141 | D10: MISC/2026/04/0009 (Cheq No 94 - Date 2026/04/29) Video editing - From Mahmoud saloum - Gaza | E10: 200 | F10: Prog_5 | G10: 1 | I10: 0 | J10: =E10*G10 -> 200 | K10: =E10*I10 -> 0
A11: 601008 | B11: Advertising & Digital Services | C11: 46146 | D11: MISC/2026/05/0004 Video editing - Jaafar Salah Abdullah Malham - Cheq No 96 - Date 2026/04/29 | E11: 300 | F11: Prog_5 | G11: 1 | I11: 0 | J11: =E11*G11 -> 300 | K11: =E11*I11 -> 0
A12: 601008 | B12: Advertising & Digital Services | C12: 46161 | D12: MISC/2026/05/0010 Gaza Video editing - 2 Video - Ghassan Ayman Fathi Ghanem - Cheq No 95 - Date 2026/04/29 | E12: 270 | F12: Prog_5 | G12: 1 | I12: 0 | J12: =E12*G12 -> 270 | K12: =E12*I12 -> 0
A13: 601008 | B13: Advertising & Digital Services | C13: 46183 | D13: MISC/2026/06/0006 Photography and videography (Filed documentation and human stories) Mahmud abu hamda - Chq No 114 - Date 2026/05/10 | E13: 3044.4 | F13: Prog_5 | G13: 1 | I13: 0 | J13: =E13*G13 -> 3044.4 | K13: =E13*I13 -> 0
A14: 601008 | B14: Advertising & Digital Services | C14: 46183 | D14: MISC/2026/06/0006 Media Coverage and One-Day Photography Session at Al-Ahli Arab Hospital – Gaza - Chq No 114 | E14: 387.026 | F14: Prog_5 | G14: 1 | I14: 0 | J14: =E14*G14 -> 387.026 | K14: =E14*I14 -> 0
A15: 601008 | B15: Advertising & Digital Services | C15: 46183 | D15: MISC/2026/06/0006 Media Coverage and One-Day Photography Session at Al-Ahli Arab Hospital – Gaza - Chq No 114 | E15: 96 | F15: Prog_5 | G15: 1 | I15: 0 | J15: =E15*G15 -> 96 | K15: =E15*I15 -> 0
A16: 601008 | B16: Advertising & Digital Services | C16: 46188 | D16: MISC/2026/06/0009 Cheque No. 129 dated 2026/06/03 - Filming Services + RHS Roll up + Printing A5 Brouchure - Jafar Salah | E16: 240 | F16: Prog_5 | G16: 1 | I16: 0 | J16: =E16*G16 -> 240 | K16: =E16*I16 -> 0
A17: 601008 | B17: Advertising & Digital Services | C17: 46195 | D17: MISC/2026/06/0012 Cheque No. 131 dated 2026/06/03 – Shafiq Nidal Shafiq – filming services, RHS roll-up banner, A5 brochure printing | E17: 83 | F17: Prog_5 | G17: 1 | I17: 0 | J17: =E17*G17 -> 83 | K17: =E17*I17 -> 0
A18: 601008 | B18: Advertising & Digital Services | C18: 46261 | D18: MISC/2026/08/0024 Cheq No 198 Date 2026/08/27 - Ghassan Ghanem Hijawi - Video Editing and color grading Service | E18: 274 | F18: Prog_5 | G18: 1 | I18: 0 | J18: =E18*G18 -> 274 | K18: =E18*I18 -> 0
A19: 601008 | B19: Advertising & Digital Services | C19: 46279 | D19: MISC/2026/09/0004 Cheque No. 199 – Jaafar Salah Abdullah Melhem – Photography services for activities involving children affected by the war in Gaza | E19: 560 | F19: Prog_5 | G19: 1 | I19: 0 | J19: =E19*G19 -> 560 | K19: =E19*I19 -> 0
A20: 120001 | B20: Goods in Transit | C20: 46022 | D20: MISC/2025/12/0010 Goods in transit up to 2025/12/31 – Settled supplier OTTOBOCK SE AND CO KGAA GERMANY | E20: 439095.63 | F20: Prog_1 | G20: 1 | I20: 0 | J20: =E20*G20 -> 439095.63 | K20: =E20*I20 -> 0
... A24: 510102 | B24: Materials & Supplies – Projects | C24: 46209 | D24: MISC/2026/07/0005 Cheq No 151 - AL- Tawaf medical equipment - Medical Supplies (POP Bandages & Plaster Powder) for Project ECP [...] | E24: 6680 | F24: Prog_1 | G24: 1 | I24: 0 | J24: =E24*G24 -> 6680 | K24: =E24*I24 -> 0
A25: 510102 | B25: Materials & Supplies – Projects | C25: 46211 | D25: MISC/2026/07/0012 Bank Transfer 2026/07/08 - Adtechnologies Unipessoal LDA - Training - 5,643.67 $ - Materials Distributed in Gaza | E25: 4022.012 | F25: Prog_1 | G25: 1 | I25: 0 | J25: =E25*G25 -> 4022.012 | K25: =E25*I25 -> 0 | L25: Training materials distributed in Gaza – allocated to prosthetics; please confirm
A26: 510102 | B26: Materials & Supplies – Projects | C26: 46244 | D26: MISC/2026/08/0012 Transfer 2026/08/10 - Upper limb prosthetic components from Al-Tawf Medical Equipment & Supplies Co., PI No. 066-26 | E26: 15671.19 | F26: Prog_1 | G26: 1 | I26: 0 | J26: =E26*G26 -> 15671.19 | K26: =E26*I26 -> 0
A27: 510102 | B27: Materials & Supplies – Projects | C27: 46279 | D27: MISC/2026/09/0005 Reversal of bank transfer amount upon receipt of supporting documents - Bank Transfer 2026/07/08 - Adtechnologies Unipessoal LDA - Training [...] | E27: 3422.257 | F27: Prog_1 | G27: 1 | I27: 0 | J27: =E27*G27 -> 3422.257 | K27: =E27*I27 -> 0 | L27: Reversal entry linked to Adtechnologies transfer – allocated to prosthetics; please confirm
A28: 510102 | B28: Materials & Supplies – Projects | C28: 46279 | D28: MISC/2026/09/0009 Transfer 2026/08/31 - Upper limb prosthetic components from Al-Tawf Medical Equipment & Supplies Co. [...] | E28: 14061 | F28: Prog_1 | G28: 1 | I28: 0 | J28: =E28*G28 -> 14061 | K28: =E28*I28 -> 0
A29: 510102 | B29: Materials & Supplies – Projects | C29: 46279 | D29: MISC/2026/09/0010 Transfer 2026/08/31 - Upper limb prosthetic components from Al-Tawf Medical Equipment & Supplies Co. [...] | E29: 9164.44 | F29: Prog_1 | G29: 1 | I29: 0 | J29: =E29*G29 -> 9164.44 | K29: =E29*I29 -> 0
A30: 601007 | B30: Office Supplies & Stationery | C30: 46226 | D30: MISC/2026/07/0019 Stationary – PSS event - Date 2026/07/16 - Majed Petty Cash | E30: 15 | F30: Prog_2 | G30: 1 | I30: 0 | J30: =E30*G30 -> 15 | K30: =E30*I30 -> 0
A31: 5010107 | B31: Patient Consultation Expenses | C31: 46219 | D31: MISC/2026/07/0016 Transfer to Belal Mohammad, MHPSS services fees 11 June 2026 to 4 July 2026, as per activity report | E31: 700 | F31: Prog_2 | G31: 1 | I31: 0 | J31: =E31*G31 -> 700 | K31: =E31*I31 -> 0
A32: 5010107 | B32: Patient Consultation Expenses | C32: 46258 | D32: MISC/2026/08/0025 Cheq No 183 to Belal Mohammad, MHPSS services fees 05 July 2026 to 30 July 2026, as per activity report | E32: 1295 | F32: Prog_2 | G32: 1 | I32: 0 | J32: =E32*G32 -> 1295 | K32: =E32*I32 -> 0
A33: 510106 | B33: Printing & Visibility – Projects | C33: 46097 | D33: MISC/2026/03/0009 Cheq No 84 - Nader Emad Al-Deen - Basel Mushtaha Printing Press, Invoice No. 309 [...] | E33: 1462.45 | F33: Prog_5 | G33: 1 | I33: 0 | J33: =E33*G33 -> 1462.45 | K33: =E33*I33 -> 0
A34: 510106 | B34: Printing & Visibility – Projects | C34: 46240 | D34: MISC/2026/08/0016 Printing, removal and installation of a new banner in Gaza by Basel Mushtaha Printing Press - Cheq No 182 | E34: 137.66 | F34: Prog_5 | G34: 1 | I34: 0 | J34: =E34*G34 -> 137.66 | K34: =E34*I34 -> 0
A35: 601004 | B35: Professional Fees (Consulting) | C35: 46254 | D35: MISC/2026/08/0008 cheq No 188 - Psychosocial consultancy fees for Maram Monadel Omar Abdelhadi, Qatar Project, July and August 2026 | E35: 1000 | F35: Prog_2 | G35: 1 | I35: 0 | J35: =E35*G35 -> 1000 | K35: =E35*I35 -> 0
A36: 5010106 | B36: Project Expense | C36: 46096 | D36: MISC/2026/03/0008 Patient Transportation Plan – Gaza - Transfer 2026/03/15 to Yabreen for Trading export import company [...] | E36: 6716.15 | F36: UNB_1 | G36: 1 | I36: 0 | J36: =E36*G36 -> 6716.15 | K36: =E36*I36 -> 0 | L36: Unbudgeted – Patient & Staff Transportation
A37: 5010106 | B37: Project Expense | C37: 46146 | D37: MISC/2026/05/0002 (Mjed Petty Cash) Transportation Cost For HABIBA - 2026/03/29 to 2026/04/01 | E37: 19.48 | F37: UNB_1 | G37: 1 | I37: 0 | J37: =E37*G37 -> 19.48 | K37: =E37*I37 -> 0 | L37: Unbudgeted – Patient & Staff Transportation
A38: 5010106 | B38: Project Expense | C38: 46160 | D38: MISC/2026/05/0011 Transporting The Child Habiba - Date 2026/05/12 | E38: 26.29 | F38: UNB_1 | G38: 1 | I38: 0 | J38: =E38*G38 -> 26.29 | K38: =E38*I38 -> 0 | L38: Unbudgeted – Patient & Staff Transportation
A39: 5010106 | B39: Project Expense | C39: 46160 | D39: MISC/2026/05/0011 Transporting the child habiba SOS to Mafaz Company and back - 2026/05/12 to 2026/05/17 | E39: 17.22 | F39: UNB_1 | G39: 1 | I39: 0 | J39: =E39*G39 -> 17.22 | K39: =E39*I39 -> 0 | L39: Unbudgeted – Patient & Staff Transportation
A40: 5010106 | B40: Project Expense | C40: 46174 | D40: MISC/2026/06/0004 Collection of prosthetic Limbs from Qatar Charity warehouse (Sahab) - 2026/05/22 | E40: 25 | F40: Prog_1 | G40: 1 | I40: 0 | J40: =E40*G40 -> 25 | K40: =E40*I40 -> 0
A41: 5010106 | B41: Project Expense | C41: 46183 | D41: MISC/2026/06/0006 Medical and surgical services contract - Ahlia Arab hospital - Chq No 114 | E41: 693.84 | F41: UNB_2 | G41: 1 | I41: 0 | J41: =E41*G41 -> 693.84 | K41: =E41*I41 -> 0 | L41: Unbudgeted – Medical Services (surgery, hospital, lab tests)
A42: 5010106 | B42: Project Expense | C42: 46183 | D42: MISC/2026/06/0006 Psychological support and cognitive development tools - Qatar Charity - Chq No 114 | E42: 969.252 | F42: Prog_2 | G42: 1 | I42: 0 | J42: =E42*G42 -> 969.252 | K42: =E42*I42 -> 0
A43: 5010106 | B43: Project Expense | C43: 46195 | D43: MISC/2026/06/0023 Cheq No 144 - Breakfast for Patients from Hamada Restaurant | E43: 200 | F43: UNB_4 | G43: 1 | I43: 0 | J43: =E43*G43 -> 200 | K43: =E43*I43 -> 0 | L43: Unbudgeted – Patient Activities, Events & Meals
A44: 5010106 | B44: Project Expense | C44: 46195 | D44: MISC/2026/06/0027 Video Filming Services for the Amputees Event, Khan Younis, Gaza – Khaled Hajaj - Cheq No 140 | E44: 240.99 | F44: Prog_5 | G44: 1 | I44: 0 | J44: =E44*G44 -> 240.99 | K44: =E44*I44 -> 0
A45: 5010106 | B45: Project Expense | C45: 46195 | D45: MISC/2026/06/0027 T-Shirt Gifts – Mohammad Al-Basheiti Company - Cheq No 140 | E45: 364.93 | F45: UNB_4 | G45: 1 | I45: 0 | J45: =E45*G45 -> 364.93 | K45: =E45*I45 -> 0 | L45: Unbudgeted – Patient Activities, Events & Meals
A46: 5010106 | B46: Project Expense | C46: 46195 | D46: MISC/2026/06/0027 Venue, Hospitality and Lunch – Sky View Restaurant – PO P00031/2026 - Cheq No 140 | E46: 794.26 | F46: UNB_4 | G46: 1 | I46: 0 | J46: =E46*G46 -> 794.26 | K46: =E46*I46 -> 0 | L46: Unbudgeted – Patient Activities, Events & Meals
A47: 5010106 | B47: Project Expense | C47: 46196 | D47: MISC/2026/06/0025 Cheque No. 147 – Ahmed Kamal Sukarieh – Lunch for Patients | E47: 562.5 | F47: UNB_4 | G47: 1 | I47: 0 | J47: =E47*G47 -> 562.5 | K47: =E47*I47 -> 0 | L47: Unbudgeted – Patient Activities, Events & Meals
A48: 5010106 | B48: Project Expense | C48: 46196 | D48: MISC/2026/06/0026 Cheque No. 143 – Nouruddin Issa Abdulkarim Qashtah – North Farm Rent for Patients | E48: 175 | F48: UNB_4 | G48: 1 | I48: 0 | J48: =E48*G48 -> 175 | K48: =E48*I48 -> 0 | L48: Unbudgeted – Patient Activities, Events & Meals
A49: 5010106 | B49: Project Expense | C49: 46209 | D49: MISC/2026/07/0002 Assistive devices / Abu Lail for medical and sports Equipment - Inv 26101554 | E49: 15 | F49: UNB_5 | G49: 1 | I49: 0 | J49: =E49*G49 -> 15 | K49: =E49*I49 -> 0 | L49: Unbudgeted – To be reclassified (miscoded job ad / unspecified assistive device)
A50: 5010106 | B50: Project Expense | C50: 46215 | D50: MISC/2026/07/0011 Bireen Import & Export Company - Shopping Vouchers No.71 | E50: 4021.44 | F50: UNB_3 | G50: 1 | I50: 0 | J50: =E50*G50 -> 4021.44 | K50: =E50*I50 -> 0 | L50: Unbudgeted – Shopping Vouchers
A51: 5010106 | B51: Project Expense | C51: 46215 | D51: MISC/2026/07/0011 Bireen Import & Export Company - Shopping Vouchers No.9 | E51: 637.2 | F51: UNB_3 | G51: 1 | I51: 0 | J51: =E51*G51 -> 637.2 | K51: =E51*I51 -> 0 | L51: Unbudgeted – Shopping Vouchers
A52: 5010106 | B52: Project Expense | C52: 46215 | D52: MISC/2026/07/0011 Bireen Import & Export Company - Shopping Vouchers for Employees no 1 | E52: 70.8 | F52: UNB_3 | G52: 1 | I52: 0 | J52: =E52*G52 -> 70.8 | K52: =E52*I52 -> 0 | L52: Unbudgeted – Shopping Vouchers
A53: 5010106 | B53: Project Expense | C53: 46215 | D53: MISC/2026/07/0011 Bireen Import & Export Company - Shopping Vouchers No.7 | E53: 594.72 | F53: UNB_3 | G53: 1 | I53: 0 | J53: =E53*G53 -> 594.72 | K53: =E53*I53 -> 0 | L53: Unbudgeted – Shopping Vouchers
A54: 5010106 | B54: Project Expense | C54: 46215 | D54: MISC/2026/07/0011 Bireen Import & Export Company - Administrative Expenses for Voucher Distribution | E54: 854.811 | F54: UNB_3 | G54: 1 | I54: 0 | J54: =E54*G54 -> 854.811 | K54: =E54*I54 -> 0 | L54: Unbudgeted – Shopping Vouchers
A55: 5010106 | B55: Project Expense | C55: 46216 | D55: MISC/2026/07/0015 Mufaz Medical Equipment and Devices Co. Invoice No. 26 - Prosthesis Training – Habibat Allah | E55: 249.98 | F55: Prog_1 | G55: 1 | I55: 0 | J55: =E55*G55 -> 249.98 | K55: =E55*I55 -> 0
A56: 5010106 | B56: Project Expense | C56: 46226 | D56: MISC/2026/07/0019 Nescafe, juice, biscuit, group session RC - Qatar Project Training - Majed petty cash | E56: 24.67 | F56: UNB_4 | G56: 1 | I56: 0 | J56: =E56*G56 -> 24.67 | K56: =E56*I56 -> 0 | L56: Unbudgeted – Patient Activities, Events & Meals
A57: 5010106 | B57: Project Expense | C57: 46230 | D57: MISC/2026/07/0025 Cheq No 171 - Alaa Dwaikat - MHPSS Activity – Children Psychosocial Support Event, 26 July 2026 | E57: 210.85 | F57: Prog_2 | G57: 1 | I57: 0 | J57: =E57*G57 -> 210.85 | K57: =E57*I57 -> 0
A58: 5010106 | B58: Project Expense | C58: 46251 | D58: MISC/2026/08/0011 Expenses related to JRC activity. Date 2026/08/04 | E58: 73 | F58: UNB_4 | G58: 1 | I58: 0 | J58: =E58*G58 -> 73 | K58: =E58*I58 -> 0 | L58: Unbudgeted – Patient Activities, Events & Meals
A59: 5010106 | B59: Project Expense | C59: 46254 | D59: MISC/2026/08/0004 Cheq No 194 - Medical laboratory tests by Biolab for patient Reham Al-Shami | E59: 155 | F59: UNB_2 | G59: 1 | I59: 0 | J59: =E59*G59 -> 155 | K59: =E59*I59 -> 0 | L59: Unbudgeted – Medical Services (surgery, hospital, lab tests)
A60: 5010106 | B60: Project Expense | C60: 46275 | D60: MISC/2026/09/0017 Cheque No. 206 – Abdali Hospital – Knee joint replacement surgery for patient Reham Al-Shami | E60: 10700 | F60: UNB_2 | G60: 1 | I60: 0 | J60: =E60*G60 -> 10700 | K60: =E60*I60 -> 0 | L60: Unbudgeted – Medical Services (surgery, hospital, lab tests)
A61: 5010106 | B61: Project Expense | C61: 46279 | D61: MISC/2026/09/0007 Cheque No. 185 – Ebdaa Tabarbour Specialized Physiotherapy Center – Physiotherapy sessions for the child Yazan | E61: 300 | F61: Prog_3 | G61: 1 | I61: 0 | J61: =E61*G61 -> 300 | K61: =E61*I61 -> 0
A62: 5010106 | B62: Project Expense | C62: 46279 | D62: MISC/2026/09/0011 Biolab Test - Reham From Gaza - Date 2026/08/20 | E62: 4 | F62: UNB_2 | G62: 1 | I62: 0 | J62: =E62*G62 -> 4 | K62: =E62*I62 -> 0 | L62: Unbudgeted – Medical Services (surgery, hospital, lab tests)
A63: 5010106 | B63: Project Expense | C63: 46279 | D63: MISC/2026/09/0011 Medical tests for one of our patients From Gaza - Date 2026/09/02 | E63: 78 | F63: UNB_2 | G63: 1 | I63: 0 | J63: =E63*G63 -> 78 | K63: =E63*I63 -> 0 | L63: Unbudgeted – Medical Services (surgery, hospital, lab tests)
A64: 510101 | B64: Project Staff Salaries | C64: 46076 | D64: MISC/2026/02/0004 Salaries of the Association’s 12 Employees in the Gaza - Jan.2026 | E64: 7479.36 | F64: Prog_2 | G64: 0.5 | H64: Prog_3 | I64: 0.5 | J64: =E64*G64 -> 3739.68 | K64: =E64*I64 -> 3739.68 | L64: Gaza salaries split 50/50 per instruction
A65: 510101 | B65: Project Staff Salaries | C65: 46076 | D65: MISC/2026/02/0005 Salaries of the Association’s 12 Employees in the Gaza - Dec.2025 | E65: 7631.54 | F65: Prog_2 | G65: 0.5 | H65: Prog_3 | I65: 0.5 | J65: =E65*G65 -> 3815.77 | K65: =E65*I65 -> 3815.77 | L65: Gaza salaries split 50/50 per instruction
A66: 510101 | B66: Project Staff Salaries | C66: 46097 | D66: MISC/2026/03/0010 Cheq No 82 - Salaries of the Association’s Employees in the Gaza - Feb.2026 | E66: 6037 | F66: Prog_2 | G66: 0.5 | H66: Prog_3 | I66: 0.5 | J66: =E66*G66 -> 3018.5 | K66: =E66*I66 -> 3018.5 | L66: Gaza salaries split 50/50 per instruction
A67: 510101 | B67: Project Staff Salaries | C67: 46121 | D67: MISC/2026/04/0006 Salaries of the Association’s Employee in the Gaza - March.2026 - Doha Abu Watfa | E67: 495.6 | F67: Prog_2 | G67: 0.5 | H67: Prog_3 | I67: 0.5 | J67: =E67*G67 -> 247.8 | K67: =E67*I67 -> 247.8 | L67: Gaza salaries split 50/50 per instruction
A68: 510101 | B68: Project Staff Salaries | C68: 46121 | D68: MISC/2026/04/0006 Salaries of the Association’s Employee in the Gaza - March.2026 - Oday Shaheen | E68: 495.6 | F68: Prog_2 | G68: 0.5 | H68: Prog_3 | I68: 0.5 | J68: =E68*G68 -> 247.8 | K68: =E68*I68 -> 247.8 | L68: Gaza salaries split 50/50 per instruction
A69: 510101 | B69: Project Staff Salaries | C69: 46121 | D69: MISC/2026/04/0006 Salaries of the Association’s Employee in the Gaza - March.2026 - Adel AL-Faqaawi | E69: 495.6 | F69: Prog_2 | G69: 0.5 | H69: Prog_3 | I69: 0.5 | J69: =E69*G69 -> 247.8 | K69: =E69*I69 -> 247.8 | L69: Gaza salaries split 50/50 per instruction
A70: 510101 | B70: Project Staff Salaries | C70: 46121 | D70: MISC/2026/04/0006 Salaries of the Association’s Employee in the Gaza - March.2026 - Baraa Elhawajri | E70: 495.6 | F70: Prog_2 | G70: 0.5 | H70: Prog_3 | I70: 0.5 | J70: =E70*G70 -> 247.8 | K70: =E70*I70 -> 247.8 | L70: Gaza salaries split 50/50 per instruction
A71: 510101 | B71: Project Staff Salaries | C71: 46121 | D71: MISC/2026/04/0006 Salaries of the Association’s Employee in the Gaza - March.2026 - Rowaa Al-Mozanan | E71: 495.6 | F71: Prog_2 | G71: 0.5 | H71: Prog_3 | I71: 0.5 | J71: =E71*G71 -> 247.8 | K71: =E71*I71 -> 247.8 | L71: Gaza salaries split 50/50 per instruction
A72: 510101 | B72: Project Staff Salaries | C72: 46121 | D72: MISC/2026/04/0006 Salaries of the Association’s Employee in the Gaza - March.2026 - Doaa Qeshta | E72: 495.6 | F72: Prog_2 | G72: 0.5 | H72: Prog_3 | I72: 0.5 | J72: =E72*G72 -> 247.8 | K72: =E72*I72 -> 247.8 | L72: Gaza salaries split 50/50 per instruction
A73: 510101 | B73: Project Staff Salaries | C73: 46121 | D73: MISC/2026/04/0006 Salaries of the Association’s Employee in the Gaza - March.2026 - Iman AL Badrasawi | E73: 495.6 | F73: Prog_2 | G73: 0.5 | H73: Prog_3 | I73: 0.5 | J73: =E73*G73 -> 247.8 | K73: =E73*I73 -> 247.8 | L73: Gaza salaries split 50/50 per instruction
A74: 510101 | B74: Project Staff Salaries | C74: 46121 | D74: MISC/2026/04/0006 Salaries of the Association’s Employee in the Gaza - March.2026 - Sobheia Aboslaieh | E74: 495.6 | F74: Prog_2 | G74: 0.5 | H74: Prog_3 | I74: 0.5 | J74: =E74*G74 -> 247.8 | K74: =E74*I74 -> 247.8 | L74: Gaza salaries split 50/50 per instruction
A75: 510101 | B75: Project Staff Salaries | C75: 46121 | D75: MISC/2026/04/0006 Salaries of the Association’s Employee in the Gaza - March.2026 - Leena Elghazali | E75: 495.6 | F75: Prog_2 | G75: 0.5 | H75: Prog_3 | I75: 0.5 | J75: =E75*G75 -> 247.8 | K75: =E75*I75 -> 247.8 | L75: Gaza salaries split 50/50 per instruction
... A131: 510101 | B131: Project Staff Salaries | C131: 46254 | D131: MISC/2026/08/0023 Salaries of the Association’s Employee in the Gaza - Aug.2026 - Abdelazez Arafat | E131: 495.6 | F131: Prog_2 | G131: 0.5 | H131: Prog_3 | I131: 0.5 | J131: =E131*G131 -> 247.8 | K131: =E131*I131 -> 247.8 | L131: Gaza salaries split 50/50 per instruction
A132: 601005 | B132: Transportation Exp | C132: 46173 | D132: MISC/2026/05/0014 Patient Transfer From the Red Crescent to AL-Touf Center - Chq No 116 - Eyad Katkat | E132: 282 | F132: UNB_1 | G132: 1 | I132: 0 | J132: =E132*G132 -> 282 | K132: =E132*I132 -> 0 | L132: Unbudgeted – Patient & Staff Transportation
A133: 601005 | B133: Transportation Exp | C133: 46244 | D133: MISC/2026/08/0009 Bireen Import & Export Company - Transportation services for staff and patients - EIN 0015 | E133: 998.811 | F133: UNB_1 | G133: 1 | I133: 0 | J133: =E133*G133 -> 998.811 | K133: =E133*I133 -> 0 | L133: Unbudgeted – Patient & Staff Transportation
A134: 601005 | B134: Transportation Exp | C134: 46244 | D134: MISC/2026/08/0010 Bireen Import & Export Company - Transportation services for staff and patients - EIN 0014 | E134: 6732.726 | F134: UNB_1 | G134: 1 | I134: 0 | J134: =E134*G134 -> 6732.726 | K134: =E134*I134 -> 0 | L134: Unbudgeted – Patient & Staff Transportation
A135: 601005 | B135: Transportation Exp | C135: 46254 | D135: MISC/2026/08/0023 Transportation Allowance of the Association’s Employee in the Gaza - Aug.2026 - Doha Abu Watfa | E135: 73.986 | F135: UNB_1 | G135: 1 | I135: 0 | J135: =E135*G135 -> 73.986 | K135: =E135*I135 -> 0 | L135: Unbudgeted – Patient & Staff Transportation
A136: 601005 | B136: Transportation Exp | C136: 46254 | D136: MISC/2026/08/0023 Transportation Allowance of the Association’s Employee in the Gaza - Aug.2026 - Oday Shaheen | E136: 73.986 | F136: UNB_1 | G136: 1 | I136: 0 | J136: =E136*G136 -> 73.986 | K136: =E136*I136 -> 0 | L136: Unbudgeted – Patient & Staff Transportation
A137: 601005 | B137: Transportation Exp | C137: 46254 | D137: MISC/2026/08/0023 Transportation Allowance of the Association’s Employee in the Gaza - Aug.2026 - Adel AL-Faqaawi | E137: 95.934 | F137: UNB_1 | G137: 1 | I137: 0 | J137: =E137*G137 -> 95.934 | K137: =E137*I137 -> 0 | L137: Unbudgeted – Patient & Staff Transportation
A138: 601005 | B138: Transportation Exp | C138: 46254 | D138: MISC/2026/08/0023 Transportation Allowance of the Association’s Employee in the Gaza - Aug.2026 - Braa Elhawajri | E138: 26.904 | F138: UNB_1 | G138: 1 | I138: 0 | J138: =E138*G138 -> 26.904 | K138: =E138*I138 -> 0 | L138: Unbudgeted – Patient & Staff Transportation
A139: 601005 | B139: Transportation Exp | C139: 46254 | D139: MISC/2026/08/0023 Transportation Allowance of the Association’s Employee in the Gaza - Aug.2026 - Rowaa AL Mozanan | E139: 26.904 | F139: UNB_1 | G139: 1 | I139: 0 | J139: =E139*G139 -> 26.904 | K139: =E139*I139 -> 0 | L139: Unbudgeted – Patient & Staff Transportation
A140: 601005 | B140: Transportation Exp | C140: 46254 | D140: MISC/2026/08/0023 Transportation Allowance of the Association’s Employee in the Gaza - Aug.2026 - Doaa Qeshta | E140: 95.934 | F140: UNB_1 | G140: 1 | I140: 0 | J140: =E140*G140 -> 95.934 | K140: =E140*I140 -> 0 | L140: Unbudgeted – Patient & Staff Transportation
A141: 601005 | B141: Transportation Exp | C141: 46254 | D141: MISC/2026/08/0023 Transportation Allowance of the Association’s Employee in the Gaza - Aug.2026 - Iman Al Badrasawi | E141: 122.484 | F141: UNB_1 | G141: 1 | I141: 0 | J141: =E141*G141 -> 122.484 | K141: =E141*I141 -> 0 | L141: Unbudgeted – Patient & Staff Transportation
A142: 601005 | B142: Transportation Exp | C142: 46254 | D142: MISC/2026/08/0023 Transportation Allowance of the Association’s Employee in the Gaza - Aug.2026 - Sobheia Aboslaieh | E142: 19.47 | F142: UNB_1 | G142: 1 | I142: 0 | J142: =E142*G142 -> 19.47 | K142: =E142*I142 -> 0 | L142: Unbudgeted – Patient & Staff Transportation
A143: 601005 | B143: Transportation Exp | C143: 46254 | D143: MISC/2026/08/0023 Transportation Allowance of the Association’s Employee in the Gaza - Aug.2026 - Leena Elghazli | E143: 19.47 | F143: UNB_1 | G143: 1 | I143: 0 | J143: =E143*G143 -> 19.47 | K143: =E143*I143 -> 0 | L143: Unbudgeted – Patient & Staff Transportation
... A156: 510103 | B156: Transportation – Projects | C156: 46279 | D156: MISC/2026/09/0013 Taxiat Company – Invoice No. 532 – patient transportation 18 July to 26 August 2026 | E156: 3627.67 | F156: UNB_1 | G156: 1 | I156: 0 | J156: =E156*G156 -> 3627.67 | K156: =E156*I156 -> 0 | L156: Unbudgeted – Patient & Staff Transportation
A157: 601019 | B157: Warehouse Expenses | C157: 46160 | D157: MISC/2026/05/0011 Worker fee For Prosthetic Withdrawal From JCHO warehouses incl. Transportation | E157: 25 | F157: Prog_1 | G157: 1 | I157: 0 | J157: =E157*G157 -> 25 | K157: =E157*I157 -> 0
